{
  "name": "e_Runner",
  "sound": "sounds/engine.wav",
  "Parts": [
    {
      "name": "Cylinder Head & Spark Plugs",
      "levels" : [
        {"MaxIntakeAirPiston": 5000, "CombustionEffiency": 0.95, "MaxRpm": 9000}
      ]
    },
    {
      "name": "Camshaft & Valves",
      "levels" : [
        {"MaxIntakeAirPiston": 2000}
      ]
    },
    {
      "name": "Intake & AirFilter",
      "levels" : [
        {"MaxIntakeAirPiston": 3000, "CombustionEffiency": 0.95}
      ]
    },
    {
      "name": "Turbo",
      "levels" : [
        {"TurboAirMult": 1}
      ]
    },
    {
      "name": "Exhaust",
      "levels" : [
        {"MaxExhaustAirPiston": 5000}
      ]
    },
    {
      "name": "ECU",
      "levels" : [
        {"CombustionEffiency": 0.9}
      ]
    },
    {
      "name": "Pistons & Crankshaft",
      "levels" : [
        {"CombustionEffiency": 0.9, "MaxRpm": 8000, "Compression": 10, "StrokeLength": 0.062}
      ]
    },
    {
      "name": "Block",
      "levels" : [
        {"PistonCount": 4, "CylinderBore": 0.085, "StrokeLength": 0.07, "IdleDrag": 0.1, "PeakTorqueRPM": 3500}
      ]
    },
    {
      "name": "Radiator",
      "levels" : [
        {"CoolingRate": 50}
      ]
    },
    {
      "name": "TransmissionDrivetrain",
      "levels" : [
        {"TransmissionEfficency": 0.9}
      ]
    }
  ]
}
